Metadata-Version: 2.4
Name: autoprognosis
Version: 0.1.22
Summary: A system for automating the design of predictive modeling pipelines tailored for clinical prognosis.
Home-page: https://www.vanderschaar-lab.com/
Author: vanderschaarlab
Author-email: 
License: Apache-2.0 license
Platform: any
Classifier: Programming Language :: Python :: 3
Classifier: Topic :: Scientific/Engineering :: Artificial Intelligence
Classifier: Intended Audience :: Healthcare Industry
Classifier: License :: OSI Approved :: BSD License
Classifier: Operating System :: OS Independent
Requires-Python: >=3.9
License-File: LICENSE
Requires-Dist: importlib-metadata; python_version < "3.8"
Requires-Dist: cloudpickle
Requires-Dist: hyperimpute>=0.1.16
Requires-Dist: joblib
Requires-Dist: lifelines
Requires-Dist: loguru
Requires-Dist: matplotlib
Requires-Dist: numpy>=1.20
Requires-Dist: optuna>=3.1.0
Requires-Dist: pandas
Requires-Dist: pydantic
Requires-Dist: pyod
Requires-Dist: redis
Requires-Dist: scikit-learn>=1.0
Requires-Dist: scipy>=1.3.2
Requires-Dist: seaborn
Requires-Dist: shap>=0.40.0
Requires-Dist: statsmodels
Requires-Dist: torch>=1.10
Provides-Extra: explainers
Requires-Dist: lime; extra == "explainers"
Requires-Dist: symbolic_pursuit; extra == "explainers"
Provides-Extra: boosting
Requires-Dist: catboost; extra == "boosting"
Requires-Dist: lightgbm; extra == "boosting"
Requires-Dist: xgboost; extra == "boosting"
Provides-Extra: tabnet
Requires-Dist: pytorch_tabnet; extra == "tabnet"
Provides-Extra: survival
Requires-Dist: pycox; extra == "survival"
Requires-Dist: torchtuples; extra == "survival"
Requires-Dist: xgbse; extra == "survival"
Provides-Extra: dashboard
Requires-Dist: plotly; extra == "dashboard"
Requires-Dist: psutil; extra == "dashboard"
Requires-Dist: pydantic; extra == "dashboard"
Requires-Dist: streamlit; extra == "dashboard"
Provides-Extra: all
Requires-Dist: lime; extra == "all"
Requires-Dist: symbolic_pursuit; extra == "all"
Requires-Dist: catboost; extra == "all"
Requires-Dist: lightgbm; extra == "all"
Requires-Dist: xgboost; extra == "all"
Requires-Dist: pytorch_tabnet; extra == "all"
Requires-Dist: pycox; extra == "all"
Requires-Dist: torchtuples; extra == "all"
Requires-Dist: xgbse; extra == "all"
Requires-Dist: plotly; extra == "all"
Requires-Dist: psutil; extra == "all"
Requires-Dist: pydantic; extra == "all"
Requires-Dist: streamlit; extra == "all"
Provides-Extra: docs
Requires-Dist: docutils<0.21; extra == "docs"
Requires-Dist: lxml[html_clean]; extra == "docs"
Requires-Dist: m2r2; extra == "docs"
Requires-Dist: mistune; extra == "docs"
Requires-Dist: nbconvert; extra == "docs"
Requires-Dist: nbsphinx; extra == "docs"
Requires-Dist: sphinx; extra == "docs"
Requires-Dist: sphinx_rtd_theme; extra == "docs"
Requires-Dist: sphinxemoji; extra == "docs"
Provides-Extra: dev
Requires-Dist: lime; extra == "dev"
Requires-Dist: symbolic_pursuit; extra == "dev"
Requires-Dist: catboost; extra == "dev"
Requires-Dist: lightgbm; extra == "dev"
Requires-Dist: xgboost; extra == "dev"
Requires-Dist: pytorch_tabnet; extra == "dev"
Requires-Dist: pycox; extra == "dev"
Requires-Dist: torchtuples; extra == "dev"
Requires-Dist: xgbse; extra == "dev"
Requires-Dist: plotly; extra == "dev"
Requires-Dist: psutil; extra == "dev"
Requires-Dist: pydantic; extra == "dev"
Requires-Dist: streamlit; extra == "dev"
Requires-Dist: docutils<0.21; extra == "dev"
Requires-Dist: lxml[html_clean]; extra == "dev"
Requires-Dist: m2r2; extra == "dev"
Requires-Dist: mistune; extra == "dev"
Requires-Dist: nbconvert; extra == "dev"
Requires-Dist: nbsphinx; extra == "dev"
Requires-Dist: sphinx; extra == "dev"
Requires-Dist: sphinx_rtd_theme; extra == "dev"
Requires-Dist: sphinxemoji; extra == "dev"
Requires-Dist: bandit; extra == "dev"
Requires-Dist: click; extra == "dev"
Requires-Dist: nbformat; extra == "dev"
Requires-Dist: pre-commit; extra == "dev"
Requires-Dist: pycox; extra == "dev"
Requires-Dist: pytest; extra == "dev"
Requires-Dist: pytest-benchmark; extra == "dev"
Requires-Dist: pytest-cov; extra == "dev"
Requires-Dist: pytest-xdist[psutil]; extra == "dev"
Requires-Dist: pytest-xprocess; extra == "dev"
Requires-Dist: ruff; extra == "dev"
Requires-Dist: setuptools; extra == "dev"
Requires-Dist: tabulate; extra == "dev"
Dynamic: license-file
